{"_type":"export","__export_format":4,"__export_date":"2020-11-24T05:51:23.994Z","__export_source":"insomnia.desktop.app:v2020.4.2","resources":[{"_id":"req_905eb2eac13a43dc924b6360e0c0f594","parentId":"fld_cf141d120115495b89876182ddfe2a96","modified":1606196863550,"created":1606196858255,"url":"{{ url }}banner","name":"Banner Home","description":"","method":"GET","body":{},"parameters":[],"headers":[],"authentication":{},"metaSortKey":-1606196858255,"isPrivate":false,"settingStoreCookies":true,"settingSendCookies":true,"settingDisableRenderRequestBody":false,"settingEncodeUrl":true,"settingRebuildPath":true,"settingFollowRedirects":"global","_type":"request"},{"_id":"fld_cf141d120115495b89876182ddfe2a96","parentId":"wrk_b07157fd165b4aa08712e02ae4a424be","modified":1606196707515,"created":1606196707515,"name":"Banner Home","description":"","environment":{},"environmentPropertyOrder":null,"metaSortKey":-1606196707515,"_type":"request_group"},{"_id":"wrk_b07157fd165b4aa08712e02ae4a424be","parentId":null,"modified":1606191964379,"created":1606191964379,"name":"UbaMoveis","description":"","scope":null,"_type":"workspace"},{"_id":"req_0f258ca6106548e6b51083937f3894c3","parentId":"fld_cf141d120115495b89876182ddfe2a96","modified":1606196754556,"created":1606196719079,"url":"{{ url }}banner","name":"Banner Home","description":"","method":"POST","body":{"mimeType":"multipart/form-data","params":[{"name":"banner","value":"","description":"","id":"pair_7834d9c363c9422997cdf6a4e1f122f1","type":"file","fileName":"C:\\Users\\junio\\Downloads\\WhatsApp Image 2020-11-09 at 10.05.58.jpeg"},{"name":"banner_mobile","value":"","description":"","id":"pair_76cd2aa7fe6347fea2a4f68fc9ca5b44","type":"file","fileName":"C:\\Users\\junio\\Downloads\\WhatsApp Image 2020-10-27 at 16.55.22.jpeg"},{"name":"link","value":"https://entreterse.com.br/confira-ordem-cronologica-das-series-da-dc-2801/6/","description":"","id":"pair_5f02203e0d504031a4f51585dc39dea6"}]},"parameters":[],"headers":[{"name":"Content-Type","value":"multipart/form-data","id":"pair_57b0f991349c4e23a5ab3b2f773605dc"}],"authentication":{},"metaSortKey":-1606196719079,"isPrivate":false,"settingStoreCookies":true,"settingSendCookies":true,"settingDisableRenderRequestBody":false,"settingEncodeUrl":true,"settingRebuildPath":true,"settingFollowRedirects":"global","_type":"request"},{"_id":"req_29cb828f9e944259a6a350aad89baaa3","parentId":"fld_805e5569ade4496682238fa3e2af5645","modified":1606195979378,"created":1606195973998,"url":"{{ url }}produtos","name":"Produtos","description":"","method":"GET","body":{},"parameters":[],"headers":[],"authentication":{},"metaSortKey":-1606195973998,"isPrivate":false,"settingStoreCookies":true,"settingSendCookies":true,"settingDisableRenderRequestBody":false,"settingEncodeUrl":true,"settingRebuildPath":true,"settingFollowRedirects":"global","_type":"request"},{"_id":"fld_805e5569ade4496682238fa3e2af5645","parentId":"wrk_b07157fd165b4aa08712e02ae4a424be","modified":1606193839217,"created":1606193839217,"name":"Produtos","description":"","environment":{},"environmentPropertyOrder":null,"metaSortKey":-1606193839217,"_type":"request_group"},{"_id":"req_0aa973e7b49c4a1a818017a14cf88d3b","parentId":"fld_805e5569ade4496682238fa3e2af5645","modified":1606195893547,"created":1606195453122,"url":"{{ url }}produtos","name":"Produtos","description":"","method":"POST","body":{"mimeType":"multipart/form-data","params":[{"name":"nome","value":"teste","description":"","id":"pair_a0bca2170e174373ba39d05a5ef8bdd4"},{"name":"preco","value":"245,50","description":"","id":"pair_a6cf8b81416f421da6bdd2b4ad659c28"},{"name":"validade_preco","value":"22/11/2020","description":"","id":"pair_7b5fd9d3d70a4f5abfb0e996ebd43b71"},{"name":"largura","value":"20","description":"","id":"pair_8324ae6c3d7e44c49c5b5218ce75d298"},{"name":"altura","value":"20","description":"","id":"pair_536f7b1b76f8493e8e1acc1fbc0d8c72"},{"name":"profundidade","value":"20","description":"","id":"pair_8e9b66de48a14d9eace34256a785379b"},{"name":"cor1","value":"#ffffff","description":"","id":"pair_1fd7009c41564a59aaa3443f98308ff5"},{"name":"cor2","value":"#000000","description":"","id":"pair_54b882de7e364229a357d10f6673c80f"},{"name":"cor3","value":"#cccccc","description":"","id":"pair_caa26be0b74e41a598d8e28324707728"},{"name":"cor4","value":"#CB3535","description":"","id":"pair_e90e2f5a4c93482d88a8a55064fcdd93"},{"name":"foto","value":"","description":"","id":"pair_631452c363b740069d5c7ddec8faeed6","type":"file","fileName":"C:\\Users\\junio\\Downloads\\image.png"},{"name":"id_categoria","value":"2","description":"","id":"pair_f4866cbf6cf748f9bc4ea93e6e7e9306"},{"name":"id_subcategoria","value":"1","description":"","id":"pair_23fee10c4ed0415a94fdca1a5114f65a"}]},"parameters":[],"headers":[{"name":"Content-Type","value":"multipart/form-data","id":"pair_85350ad9122c4f98a7b3ed13637de13d"}],"authentication":{},"metaSortKey":-1606195453122,"isPrivate":false,"settingStoreCookies":true,"settingSendCookies":true,"settingDisableRenderRequestBody":false,"settingEncodeUrl":true,"settingRebuildPath":true,"settingFollowRedirects":"global","_type":"request"},{"_id":"req_dfa442b59b5e4c238c0feb5b10a574f7","parentId":"fld_3b04be962cb54112a7b7092e4399f308","modified":1606193103795,"created":1606193099183,"url":"{{ url }}newsletter","name":"Newsletter","description":"","method":"GET","body":{},"parameters":[],"headers":[],"authentication":{},"metaSortKey":-1606193099183,"isPrivate":false,"settingStoreCookies":true,"settingSendCookies":true,"settingDisableRenderRequestBody":false,"settingEncodeUrl":true,"settingRebuildPath":true,"settingFollowRedirects":"global","_type":"request"},{"_id":"fld_3b04be962cb54112a7b7092e4399f308","parentId":"wrk_b07157fd165b4aa08712e02ae4a424be","modified":1606192794903,"created":1606192794903,"name":"Newsletter","description":"","environment":{},"environmentPropertyOrder":null,"metaSortKey":-1606192794903,"_type":"request_group"},{"_id":"req_a7066c10afe0436ca7d83eb2d6ce2535","parentId":"fld_3b04be962cb54112a7b7092e4399f308","modified":1606192951325,"created":1606192807863,"url":"{{ url }}newsletter","name":"NewsLetter","description":"","method":"POST","body":{"mimeType":"application/x-www-form-urlencoded","params":[{"name":"whatsapp","value":"(24) 98158-4658","description":"","id":"pair_511d1a4e8d064d399b4a5f5d9a25cfa7"}]},"parameters":[],"headers":[{"name":"Content-Type","value":"application/x-www-form-urlencoded","id":"pair_ac3dfd2875a849a5a4288c5c0d320fcd"}],"authentication":{},"metaSortKey":-1606192807863,"isPrivate":false,"settingStoreCookies":true,"settingSendCookies":true,"settingDisableRenderRequestBody":false,"settingEncodeUrl":true,"settingRebuildPath":true,"settingFollowRedirects":"global","_type":"request"},{"_id":"req_2ce0406e7f5449e4a281360a15852137","parentId":"fld_a0454a62e94f473c8612be61c508c743","modified":1606192482890,"created":1606192475549,"url":"{{ url }}curriculos","name":"Curriculos","description":"","method":"GET","body":{},"parameters":[],"headers":[],"authentication":{},"metaSortKey":-1606192475549,"isPrivate":false,"settingStoreCookies":true,"settingSendCookies":true,"settingDisableRenderRequestBody":false,"settingEncodeUrl":true,"settingRebuildPath":true,"settingFollowRedirects":"global","_type":"request"},{"_id":"fld_a0454a62e94f473c8612be61c508c743","parentId":"wrk_b07157fd165b4aa08712e02ae4a424be","modified":1606192458949,"created":1606192458949,"name":"Curriculos","description":"","environment":{},"environmentPropertyOrder":null,"metaSortKey":-1606192458949,"_type":"request_group"},{"_id":"req_d1cf767e96c34e5695c9d8bdc0c9e1ad","parentId":"fld_a0454a62e94f473c8612be61c508c743","modified":1606192464206,"created":1606191981448,"url":"{{ url }}curriculos","name":"Curriculos","description":"","method":"POST","body":{"mimeType":"multipart/form-data","params":[{"name":"nome","value":"teste","description":"","id":"pair_71b9727ad9164060949c437910dcc986"},{"name":"email","value":"teste@teste.com","description":"","id":"pair_0c15b8f71d3841e38206e9ed8de73ae8"},{"name":"telefone","value":"24981584658","description":"","id":"pair_fd5811fb01a541b5a2df7022ecd779e7"},{"name":"endereco","value":"rua oito, numero 73, morada da granja barra mansa","description":"","id":"pair_3abac0405a504f77bd86940453d9df40"},{"name":"sexo","value":"m","description":"","id":"pair_228588fc98724300844f946e6339e0a6"},{"name":"data_nascimento","value":"01/10/1997","description":"","id":"pair_413a288015ad45c384df6d108b0f22c2"},{"name":"curriculo","value":"","description":"","id":"pair_ec878d9a92e34286ba54c12e9cd1d7da","type":"file","fileName":"C:\\Users\\junio\\OneDrive\\Currículo Sergio Paulo.docx.pdf"}]},"parameters":[],"headers":[{"name":"Content-Type","value":"multipart/form-data","id":"pair_2aab4cb16b5149b29797d169d4e84963"}],"authentication":{},"metaSortKey":-1606192220198.5,"isPrivate":false,"settingStoreCookies":true,"settingSendCookies":true,"settingDisableRenderRequestBody":false,"settingEncodeUrl":true,"settingRebuildPath":true,"settingFollowRedirects":"global","_type":"request"},{"_id":"env_f58414f6540b2676e090aee69b841276988c2742","parentId":"wrk_b07157fd165b4aa08712e02ae4a424be","modified":1606192099715,"created":1606191964604,"name":"Base Environment","data":{"url":"http://localhost:3333/"},"dataPropertyOrder":{"&":["url"]},"color":null,"isPrivate":false,"metaSortKey":1606191964604,"_type":"environment"},{"_id":"jar_f58414f6540b2676e090aee69b841276988c2742","parentId":"wrk_b07157fd165b4aa08712e02ae4a424be","modified":1606191964612,"created":1606191964612,"name":"Default Jar","cookies":[],"_type":"cookie_jar"},{"_id":"spc_c30438806eab4d23b3bddd8302611a69","parentId":"wrk_b07157fd165b4aa08712e02ae4a424be","modified":1606191964399,"created":1606191964399,"fileName":"UbaMoveis","contents":"","contentType":"yaml","_type":"api_spec"},{"_id":"env_3be8699972cf4de2a4a56776f7c8281c","parentId":"env_f58414f6540b2676e090aee69b841276988c2742","modified":1606192125166,"created":1606192112023,"name":"Local","data":{"url":"http://localhost:3333/"},"dataPropertyOrder":{"&":["url"]},"color":"#676acb","isPrivate":false,"metaSortKey":1606192112023,"_type":"environment"}]}